{
  "userFeed": {
    "indexingMode": "consistent",
    "automatic": true,
    "includedPaths": [
      { "path": "/*" }
    ],
    "excludedPaths": [
      { "path": "/\"_etag\"/?" }
    ],
    "compositeIndexes": [
      [
        { "path": "/recipientId", "order": "ascending" },
        { "path": "/createdAt", "order": "descending" }
      ],
      [
        { "path": "/recipientId", "order": "ascending" },
        { "path": "/relevanceScore", "order": "descending" },
        { "path": "/createdAt", "order": "descending" }
      ]
    ]
  },
  "posts_v2": {
    "indexingMode": "consistent",
    "automatic": true,
    "includedPaths": [
      { "path": "/*" }
    ],
    "excludedPaths": [
      { "path": "/\"_etag\"/?" }
    ],
    "compositeIndexes": [
      [
        { "path": "/authorId", "order": "ascending" },
        { "path": "/createdAt", "order": "descending" }
      ],
      [
        { "path": "/status", "order": "ascending" },
        { "path": "/createdAt", "order": "descending" }
      ],
      [
        { "path": "/metadata/category", "order": "ascending" },
        { "path": "/createdAt", "order": "descending" }
      ],
      [
        { "path": "/score", "order": "descending" },
        { "path": "/createdAt", "order": "descending" }
      ]
    ]
  },
  "reactions": {
    "indexingMode": "consistent",
    "automatic": true,
    "includedPaths": [
      { "path": "/*" }
    ],
    "excludedPaths": [
      { "path": "/\"_etag\"/?" }
    ],
    "compositeIndexes": [
      [
        { "path": "/postId", "order": "ascending" },
        { "path": "/type", "order": "ascending" },
        { "path": "/createdAt", "order": "descending" }
      ],
      [
        { "path": "/userId", "order": "ascending" },
        { "path": "/createdAt", "order": "descending" }
      ]
    ]
  },
  "notifications": {
    "indexingMode": "consistent",
    "automatic": true,
    "includedPaths": [
      { "path": "/*" }
    ],
    "excludedPaths": [
      { "path": "/\"_etag\"/?" }
    ],
    "compositeIndexes": [
      [
        { "path": "/recipientId", "order": "ascending" },
        { "path": "/read", "order": "ascending" },
        { "path": "/createdAt", "order": "descending" }
      ]
    ],
    "defaultTtl": 2592000
  },
  "counters": {
    "indexingMode": "consistent",
    "automatic": true,
    "includedPaths": [
      { "path": "/*" }
    ],
    "excludedPaths": [
      { "path": "/\"_etag\"/?" }
    ],
    "compositeIndexes": [
      [
        { "path": "/subjectId", "order": "ascending" },
        { "path": "/type", "order": "ascending" }
      ]
    ],
    "defaultTtl": 7776000
  },
  "publicProfiles": {
    "indexingMode": "consistent",
    "automatic": true,
    "includedPaths": [
      { "path": "/*" }
    ],
    "excludedPaths": [
      { "path": "/\"_etag\"/?" },
      { "path": "/bio/?" }
    ]
  }
}